turbo_docs-2.0.8.dist-info/METADATA
turbo_docs-2.0.8.dist-info/WHEEL
turbo_docs-2.0.8.dist-info/entry_points.txt
turbo_docs/__init__.py
turbo_docs/cli.py
turbo_docs/constants.py
turbo_docs/llm.py
turbo_docs/readme.py
turbo_docs-2.0.8.dist-info/RECORD
