Metadata-Version: 2.1
Name: turbo-docs
Version: 2.0.8
Summary: Default template for PDM package
Author-Email: voynow <voynow99@gmail.com>
License: MIT
Requires-Python: >=3.11
Requires-Dist: tiktoken>=0.9.0
Requires-Dist: openai>=1.63.2
Requires-Dist: pydantic>=2.10.6
Requires-Dist: python-dotenv>=1.0.1
